README.md
setup.py
binary_utils/__init__.py
binary_utils/binary_converter.py
binary_utils/binary_stream.py
binary_utils.egg-info/PKG-INFO
binary_utils.egg-info/SOURCES.txt
binary_utils.egg-info/dependency_links.txt
binary_utils.egg-info/top_level.txt