Metadata-Version: 1.1
Name: binary-utils
Version: 1.3
Summary: Podrum's Binary Utilities.
Home-page: https://github.com/Podrum/binary_utils
Author: Podrum
Author-email: UNKNOWN
License: MIT
Keywords: utils,binary,python3
Platform: UNKNOWN
Classifier: Development Status :: 5 - Production/Stable
Classifier: Intended Audience :: Developers
Classifier: Topic :: Software Development :: Libraries
Classifier: License :: OSI Approved :: MIT License
Classifier: Programming Language :: Python :: 3.5
Classifier: Programming Language :: Python :: 3.6
Classifier: Programming Language :: Python :: 3.7
Classifier: Programming Language :: Python :: 3.8
Classifier: Programming Language :: Python :: 3.9
Classifier: Programming Language :: Python :: 3.10
